LICENSE.txt
README.md
pwhois
setup.py
pythonwhois/__init__.py
pythonwhois/airports.dat
pythonwhois/countries.dat
pythonwhois/countries3.dat
pythonwhois/net.py
pythonwhois/parse.py
pythonwhois/shared.py
pythonwhois/states_au.dat
pythonwhois/states_ca.dat
pythonwhois/states_us.dat
pythonwhois_alt.egg-info/PKG-INFO
pythonwhois_alt.egg-info/SOURCES.txt
pythonwhois_alt.egg-info/dependency_links.txt
pythonwhois_alt.egg-info/requires.txt
pythonwhois_alt.egg-info/top_level.txt