Metadata-Version: 2.1
Name: pythonwhois-alt
Version: 2.4.6
Summary: Module for retrieving and parsing the WHOIS data for a domain. Supports most domains. No dependencies.
Home-page: https://github.com/kilgoretrout1985/pythonwhois-alt
Author: Yuriy Zemskov
Author-email: zemskyura@gmail.com
License: WTFPL
Keywords: whois nic domain
Platform: UNKNOWN
Classifier: Environment :: Web Environment
Classifier: Intended Audience :: Developers
Classifier: Operating System :: OS Independent
Classifier: Programming Language :: Python
Classifier: Programming Language :: Python :: 2
Classifier: Programming Language :: Python :: 2.7
Classifier: Programming Language :: Python :: 3
Classifier: Programming Language :: Python :: 3.7
Classifier: Programming Language :: Python :: 3.8
Classifier: Programming Language :: Python :: 3.9
Classifier: Programming Language :: Python :: 3.10
Classifier: Programming Language :: Python :: 3.11
Classifier: Topic :: Internet :: Name Service (DNS)
Provides: pythonwhois
